README.md
binspect/main.py
binspect-0.1.1.dist-info/METADATA
binspect-0.1.1.dist-info/WHEEL
binspect-0.1.1.dist-info/entry_points.txt
binspect-0.1.1.dist-info/licenses/LICENSE
binspect-0.1.1.dist-info/RECORD
