Metadata-Version: 2.4
Name: binspect
Version: 0.1.1
Summary: Add a layer of protection to piped bash installs
Author: Thomas McKanna
License-Expression: MIT
License-File: LICENSE
Requires-Python: >=3.8
Requires-Dist: litellm==1.55.12
Requires-Dist: requests==2.32.3
Requires-Dist: rich==13.9.4
